package01yxx/__init__.py
package01yxx/main.py
package01yxx-0.1.0.dist-info/LICENSE
package01yxx-0.1.0.dist-info/METADATA
package01yxx-0.1.0.dist-info/WHEEL
package01yxx-0.1.0.dist-info/top_level.txt
package01yxx-0.1.0.dist-info/RECORD
