Metadata-Version: 2.1
Name: package01yxx
Version: 0.1.0
Summary: My awesome module
Author: Your Name
Author-email: your.email@example.com
License-File: LICENSE
Requires-Dist: selenium
Requires-Dist: pytest
